cz_conventionalish.py
questions.py
conventionalish-0.1.1.dist-info/METADATA
conventionalish-0.1.1.dist-info/WHEEL
conventionalish-0.1.1.dist-info/RECORD
