Metadata-Version: 2.1
Name: conventionalish
Version: 0.1.1
Summary: 
Author: Shay Hill
Author-email: shay_public@hotmail.com
Requires-Python: >=3.8,<4.0
Classifier: Programming Language :: Python :: 3
Classifier: Programming Language :: Python :: 3.8
Classifier: Programming Language :: Python :: 3.9
Classifier: Programming Language :: Python :: 3.10
Classifier: Programming Language :: Python :: 3.11
Requires-Dist: commitizen (>=2.39.1,<3.0.0)
